Updatepythonaistv/__init__.py
Updatepythonaistv/cli.py
updatepythonaistv-1.0.3.dist-info/METADATA
updatepythonaistv-1.0.3.dist-info/WHEEL
updatepythonaistv-1.0.3.dist-info/entry_points.txt
updatepythonaistv-1.0.3.dist-info/top_level.txt
updatepythonaistv-1.0.3.dist-info/RECORD
